meshcatstic/client.py
meshcatstic/devices.json
meshcatstic/flash.py
meshcatstic/server.py
meshcatstic/socat.py
meshcatstic/utils.py
meshcatstic-0.1.3.dist-info/LICENSE
meshcatstic-0.1.3.dist-info/METADATA
meshcatstic-0.1.3.dist-info/WHEEL
meshcatstic-0.1.3.dist-info/entry_points.txt
meshcatstic-0.1.3.dist-info/RECORD
