Metadata-Version: 2.1
Name: meshcatstic
Version: 0.1.3
Summary: Meshtastic serial device discovery gateway service and client built around socat plus other tooling
License: GNU GPLv3
Author: Ben Meadors
Author-email: benmmeadors@gmail.com
Requires-Python: >=3.10,<3.13
Classifier: License :: Other/Proprietary License
Classifier: Programming Language :: Python :: 3
Classifier: Programming Language :: Python :: 3.10
Classifier: Programming Language :: Python :: 3.11
Classifier: Programming Language :: Python :: 3.12
Requires-Dist: adafruit-nrfutil (>=0.5.3.post16,<0.6.0)
Requires-Dist: colorama (>=0.4.6,<0.5.0)
Requires-Dist: esptool (>=4.8.1,<5.0.0)
Requires-Dist: fastapi (>=0.115.1,<0.116.0)
Requires-Dist: meshtastic (>=2.5.1,<3.0.0)
Requires-Dist: pyserial (>=3.5,<4.0)
Requires-Dist: python-multipart (>=0.0.12,<0.0.13)
Requires-Dist: typer (>=0.12.5,<0.13.0)
Requires-Dist: uvicorn (>=0.31.1,<0.32.0)
